<?xml version="1.0" encoding="UTF-8"?>

<!-- generated on Tue Oct 25 00:52:21 2022 by Eclipse SUMO sumo Version 1.8.0
<configuration xmlns:xsi="http://www.w3.org/2001/XMLSchema-instance" xsi:noNamespaceSchemaLocation="http://sumo.dlr.de/xsd/sumoConfiguration.xsd">

    <input>
        <net-file value="Area_pedonale.net.xml"/>
        <route-files value="Area_pedonale.rou.xml"/>
    </input>

    <output>
        <tripinfo-output value="Areapedonale_out_3.xml"/>
    </output>

    <time>
        <begin value="0"/>
        <end value="50"/>
    </time>

</configuration>
-->

<tripinfos xmlns:xsi="http://www.w3.org/2001/XMLSchema-instance" xsi:noNamespaceSchemaLocation="http://sumo.dlr.de/xsd/tripinfo_file.xsd">
</tripinfos>
