<?xml version="1.0" encoding="UTF-8"?>

<!-- generated on 2022-12-07 17:38:33.565022 by randomTrips.py v1_15_0+0682-ef022823415
<configuration>
    <end value="1000"/>
    <length value="True"/>
    <max-distance value="800.0"/>
    <net-file value="/home/toore/Tirocinio_SUMO/Scenario/MOdifica_area_pedonale/Area_pedonale.net.xml"/>
    <period value="1.4"/>
    <persontrips value="True"/>
    <random value="True"/>
    <random-depart value="True"/>
    <route-file value="persontrip.rou.xml"/>
    <seed value="100000"/>
    <trip-attributes value="type=&quot;DEFAULT_PEDTYPE&quot;"/>
</configuration>
-->

<!-- generated on Wed Dec  7 17:38:33 2022 by Eclipse SUMO duarouter Version 1.8.0
<configuration xmlns:xsi="http://www.w3.org/2001/XMLSchema-instance" xsi:noNamespaceSchemaLocation="http://sumo.dlr.de/xsd/duarouterConfiguration.xsd">

    <input>
        <net-file value="/home/toore/Tirocinio_SUMO/Scenario/MOdifica_area_pedonale/Area_pedonale.net.xml"/>
        <route-files value="trips.trips.xml"/>
    </input>

    <output>
        <output-file value="persontrip.rou.xml"/>
        <alternatives-output value="NUL"/>
    </output>

    <time>
        <begin value="0"/>
        <end value="1000"/>
    </time>

    <report>
        <no-warnings value="true"/>
        <ignore-errors value="true"/>
        <no-step-log value="true"/>
    </report>

</configuration>
-->

<routes xmlns:xsi="http://www.w3.org/2001/XMLSchema-instance" xsi:noNamespaceSchemaLocation="http://sumo.dlr.de/xsd/routes_file.xsd">
    <person id="0" type="DEFAULT_PEDTYPE" depart="1.80">
        <walk edges="-gneE0"/>
    </person>
    <person id="1" type="DEFAULT_PEDTYPE" depart="3.60">
        <walk edges="gneE0"/>
    </person>
    <person id="2" type="DEFAULT_PEDTYPE" depart="4.00">
        <walk edges="-gneE0 gneE0"/>
    </person>
    <person id="3" type="DEFAULT_PEDTYPE" depart="4.00">
        <walk edges="gneE0"/>
    </person>
    <person id="5" type="DEFAULT_PEDTYPE" depart="5.60">
        <walk edges="-gneE0 gneE0"/>
    </person>
    <person id="6" type="DEFAULT_PEDTYPE" depart="8.00">
        <walk edges="-gneE0"/>
    </person>
    <person id="8" type="DEFAULT_PEDTYPE" depart="9.80">
        <walk edges="-gneE0 gneE0"/>
    </person>
    <person id="10" type="DEFAULT_PEDTYPE" depart="11.80">
        <walk edges="-gneE0"/>
    </person>
    <person id="11" type="DEFAULT_PEDTYPE" depart="12.00">
        <walk edges="-gneE0 gneE0"/>
    </person>
    <person id="13" type="DEFAULT_PEDTYPE" depart="13.20">
        <walk edges="-gneE0 gneE0"/>
    </person>
    <person id="14" type="DEFAULT_PEDTYPE" depart="16.20">
        <walk edges="gneE0 gneE2"/>
    </person>
    <person id="15" type="DEFAULT_PEDTYPE" depart="19.00">
        <walk edges="gneE0 gneE2"/>
    </person>
    <person id="18" type="DEFAULT_PEDTYPE" depart="23.00">
        <walk edges="gneE0 -gneE0"/>
    </person>
    <person id="19" type="DEFAULT_PEDTYPE" depart="23.40">
        <walk edges="gneE0 -gneE0"/>
    </person>
    <person id="20" type="DEFAULT_PEDTYPE" depart="24.80">
        <walk edges="gneE2 gneE0"/>
    </person>
    <person id="21" type="DEFAULT_PEDTYPE" depart="29.00">
        <walk edges="gneE0 -gneE0"/>
    </person>
    <person id="23" type="DEFAULT_PEDTYPE" depart="31.80">
        <walk edges="-gneE0 gneE0"/>
    </person>
    <person id="29" type="DEFAULT_PEDTYPE" depart="43.20">
        <walk edges="gneE0"/>
    </person>
    <person id="30" type="DEFAULT_PEDTYPE" depart="43.20">
        <walk edges="gneE0 -gneE0"/>
    </person>
    <person id="33" type="DEFAULT_PEDTYPE" depart="47.80">
        <walk edges="gneE0"/>
    </person>
    <person id="34" type="DEFAULT_PEDTYPE" depart="52.40">
        <walk edges="-gneE0"/>
    </person>
    <person id="35" type="DEFAULT_PEDTYPE" depart="53.40">
        <walk edges="-gneE0"/>
    </person>
    <person id="36" type="DEFAULT_PEDTYPE" depart="54.20">
        <walk edges="gneE0 -gneE0"/>
    </person>
    <person id="37" type="DEFAULT_PEDTYPE" depart="55.20">
        <walk edges="gneE0"/>
    </person>
    <person id="38" type="DEFAULT_PEDTYPE" depart="55.60">
        <walk edges="gneE1 gneE3"/>
    </person>
    <person id="40" type="DEFAULT_PEDTYPE" depart="59.20">
        <walk edges="gneE0"/>
    </person>
    <person id="41" type="DEFAULT_PEDTYPE" depart="62.80">
        <walk edges="gneE3"/>
    </person>
    <person id="42" type="DEFAULT_PEDTYPE" depart="63.00">
        <walk edges="-gneE0 gneE2"/>
    </person>
    <person id="45" type="DEFAULT_PEDTYPE" depart="64.40">
        <walk edges="gneE0"/>
    </person>
    <person id="47" type="DEFAULT_PEDTYPE" depart="65.80">
        <walk edges="gneE1 gneE3"/>
    </person>
    <person id="48" type="DEFAULT_PEDTYPE" depart="66.80">
        <walk edges="gneE0 gneE2"/>
    </person>
    <person id="49" type="DEFAULT_PEDTYPE" depart="67.20">
        <walk edges="-gneE0 gneE0"/>
    </person>
    <person id="52" type="DEFAULT_PEDTYPE" depart="74.80">
        <walk edges="gneE0"/>
    </person>
    <person id="53" type="DEFAULT_PEDTYPE" depart="75.20">
        <walk edges="gneE3"/>
    </person>
    <person id="56" type="DEFAULT_PEDTYPE" depart="77.80">
        <walk edges="-gneE0"/>
    </person>
    <person id="59" type="DEFAULT_PEDTYPE" depart="81.20">
        <walk edges="gneE0 -gneE0"/>
    </person>
    <person id="61" type="DEFAULT_PEDTYPE" depart="83.80">
        <walk edges="-gneE0"/>
    </person>
    <person id="62" type="DEFAULT_PEDTYPE" depart="84.40">
        <walk edges="gneE0 gneE2"/>
    </person>
    <person id="63" type="DEFAULT_PEDTYPE" depart="84.80">
        <walk edges="-gneE0 gneE0"/>
    </person>
    <person id="65" type="DEFAULT_PEDTYPE" depart="87.40">
        <walk edges="gneE0 -gneE0"/>
    </person>
    <person id="70" type="DEFAULT_PEDTYPE" depart="94.00">
        <walk edges="-gneE0 gneE0"/>
    </person>
    <person id="71" type="DEFAULT_PEDTYPE" depart="94.40">
        <walk edges="gneE0 -gneE0"/>
    </person>
    <person id="72" type="DEFAULT_PEDTYPE" depart="94.80">
        <walk edges="-gneE0 gneE0"/>
    </person>
    <person id="74" type="DEFAULT_PEDTYPE" depart="96.00">
        <walk edges="gneE3"/>
    </person>
    <person id="77" type="DEFAULT_PEDTYPE" depart="102.00">
        <walk edges="gneE0 -gneE0"/>
    </person>
    <person id="78" type="DEFAULT_PEDTYPE" depart="102.60">
        <walk edges="gneE3 gneE1"/>
    </person>
    <person id="79" type="DEFAULT_PEDTYPE" depart="103.60">
        <walk edges="gneE0"/>
    </person>
    <person id="80" type="DEFAULT_PEDTYPE" depart="105.40">
        <walk edges="gneE3"/>
    </person>
    <person id="81" type="DEFAULT_PEDTYPE" depart="106.20">
        <walk edges="gneE1"/>
    </person>
    <person id="82" type="DEFAULT_PEDTYPE" depart="107.20">
        <walk edges="gneE2 -gneE0"/>
    </person>
    <person id="83" type="DEFAULT_PEDTYPE" depart="107.40">
        <walk edges="gneE0"/>
    </person>
    <person id="84" type="DEFAULT_PEDTYPE" depart="110.20">
        <walk edges="gneE0 -gneE0"/>
    </person>
    <person id="85" type="DEFAULT_PEDTYPE" depart="110.40">
        <walk edges="-gneE0"/>
    </person>
    <person id="86" type="DEFAULT_PEDTYPE" depart="111.20">
        <walk edges="-gneE0 gneE0"/>
    </person>
    <person id="87" type="DEFAULT_PEDTYPE" depart="112.40">
        <walk edges="gneE0 -gneE0"/>
    </person>
    <person id="89" type="DEFAULT_PEDTYPE" depart="115.60">
        <walk edges="gneE2 gneE0"/>
    </person>
    <person id="90" type="DEFAULT_PEDTYPE" depart="116.20">
        <walk edges="-gneE0"/>
    </person>
    <person id="91" type="DEFAULT_PEDTYPE" depart="116.80">
        <walk edges="gneE0"/>
    </person>
    <person id="92" type="DEFAULT_PEDTYPE" depart="118.80">
        <walk edges="gneE2 gneE0"/>
    </person>
    <person id="93" type="DEFAULT_PEDTYPE" depart="119.40">
        <walk edges="gneE0"/>
    </person>
    <person id="94" type="DEFAULT_PEDTYPE" depart="119.40">
        <walk edges="gneE0 -gneE0"/>
    </person>
    <person id="95" type="DEFAULT_PEDTYPE" depart="121.40">
        <walk edges="gneE2 -gneE0"/>
    </person>
    <person id="98" type="DEFAULT_PEDTYPE" depart="123.60">
        <walk edges="-gneE0 gneE0"/>
    </person>
    <person id="99" type="DEFAULT_PEDTYPE" depart="125.80">
        <walk edges="gneE0"/>
    </person>
    <person id="101" type="DEFAULT_PEDTYPE" depart="128.40">
        <walk edges="gneE0 -gneE0"/>
    </person>
    <person id="102" type="DEFAULT_PEDTYPE" depart="128.80">
        <walk edges="gneE2 gneE0"/>
    </person>
    <person id="103" type="DEFAULT_PEDTYPE" depart="129.20">
        <walk edges="-gneE0"/>
    </person>
    <person id="104" type="DEFAULT_PEDTYPE" depart="129.40">
        <walk edges="gneE2 gneE0"/>
    </person>
    <person id="105" type="DEFAULT_PEDTYPE" depart="130.00">
        <walk edges="-gneE0 gneE2"/>
    </person>
    <person id="107" type="DEFAULT_PEDTYPE" depart="130.60">
        <walk edges="-gneE0 gneE0"/>
    </person>
    <person id="110" type="DEFAULT_PEDTYPE" depart="139.60">
        <walk edges="gneE0"/>
    </person>
    <person id="111" type="DEFAULT_PEDTYPE" depart="141.20">
        <walk edges="gneE0 -gneE0"/>
    </person>
    <person id="113" type="DEFAULT_PEDTYPE" depart="141.80">
        <walk edges="gneE0 -gneE0"/>
    </person>
    <person id="114" type="DEFAULT_PEDTYPE" depart="144.60">
        <walk edges="-gneE0 gneE2"/>
    </person>
    <person id="115" type="DEFAULT_PEDTYPE" depart="145.40">
        <walk edges="-gneE0 gneE2"/>
    </person>
    <person id="116" type="DEFAULT_PEDTYPE" depart="146.40">
        <walk edges="gneE0"/>
    </person>
    <person id="119" type="DEFAULT_PEDTYPE" depart="154.20">
        <walk edges="gneE0"/>
    </person>
    <person id="122" type="DEFAULT_PEDTYPE" depart="162.60">
        <walk edges="-gneE0 gneE0"/>
    </person>
    <person id="123" type="DEFAULT_PEDTYPE" depart="162.80">
        <walk edges="gneE0 -gneE0"/>
    </person>
    <person id="124" type="DEFAULT_PEDTYPE" depart="164.20">
        <walk edges="-gneE0 gneE0"/>
    </person>
    <person id="126" type="DEFAULT_PEDTYPE" depart="168.80">
        <walk edges="-gneE0"/>
    </person>
    <person id="127" type="DEFAULT_PEDTYPE" depart="171.60">
        <walk edges="gneE0"/>
    </person>
    <person id="128" type="DEFAULT_PEDTYPE" depart="174.20">
        <walk edges="-gneE0 gneE0"/>
    </person>
    <person id="129" type="DEFAULT_PEDTYPE" depart="175.40">
        <walk edges="-gneE0 gneE0"/>
    </person>
    <person id="130" type="DEFAULT_PEDTYPE" depart="176.20">
        <walk edges="-gneE0 gneE0"/>
    </person>
    <person id="131" type="DEFAULT_PEDTYPE" depart="177.60">
        <walk edges="-gneE0"/>
    </person>
    <person id="132" type="DEFAULT_PEDTYPE" depart="178.40">
        <walk edges="gneE0 -gneE0"/>
    </person>
    <person id="134" type="DEFAULT_PEDTYPE" depart="182.60">
        <walk edges="-gneE0 gneE0"/>
    </person>
    <person id="136" type="DEFAULT_PEDTYPE" depart="184.60">
        <walk edges="gneE0 -gneE0"/>
    </person>
    <person id="137" type="DEFAULT_PEDTYPE" depart="186.00">
        <walk edges="gneE0"/>
    </person>
    <person id="138" type="DEFAULT_PEDTYPE" depart="187.40">
        <walk edges="gneE1 gneE3"/>
    </person>
    <person id="141" type="DEFAULT_PEDTYPE" depart="190.20">
        <walk edges="-gneE0 gneE0"/>
    </person>
    <person id="143" type="DEFAULT_PEDTYPE" depart="191.60">
        <walk edges="gneE0 -gneE0"/>
    </person>
    <person id="144" type="DEFAULT_PEDTYPE" depart="193.60">
        <walk edges="gneE1 gneE3"/>
    </person>
    <person id="145" type="DEFAULT_PEDTYPE" depart="195.00">
        <walk edges="gneE2 -gneE0"/>
    </person>
    <person id="146" type="DEFAULT_PEDTYPE" depart="195.80">
        <walk edges="-gneE0"/>
    </person>
    <person id="149" type="DEFAULT_PEDTYPE" depart="200.20">
        <walk edges="gneE2 gneE0"/>
    </person>
    <person id="150" type="DEFAULT_PEDTYPE" depart="200.60">
        <walk edges="gneE0 gneE2"/>
    </person>
    <person id="154" type="DEFAULT_PEDTYPE" depart="204.20">
        <walk edges="-gneE0"/>
    </person>
    <person id="155" type="DEFAULT_PEDTYPE" depart="205.00">
        <walk edges="-gneE0"/>
    </person>
    <person id="156" type="DEFAULT_PEDTYPE" depart="209.60">
        <walk edges="-gneE0 gneE0"/>
    </person>
    <person id="159" type="DEFAULT_PEDTYPE" depart="211.00">
        <walk edges="gneE0"/>
    </person>
    <person id="160" type="DEFAULT_PEDTYPE" depart="211.40">
        <walk edges="gneE2 -gneE0"/>
    </person>
    <person id="162" type="DEFAULT_PEDTYPE" depart="214.80">
        <walk edges="-gneE0"/>
    </person>
    <person id="165" type="DEFAULT_PEDTYPE" depart="219.60">
        <walk edges="gneE0 gneE2"/>
    </person>
    <person id="166" type="DEFAULT_PEDTYPE" depart="220.20">
        <walk edges="gneE2 -gneE0"/>
    </person>
    <person id="170" type="DEFAULT_PEDTYPE" depart="229.60">
        <walk edges="-gneE0 gneE0"/>
    </person>
    <person id="171" type="DEFAULT_PEDTYPE" depart="231.20">
        <walk edges="gneE0 -gneE0"/>
    </person>
    <person id="172" type="DEFAULT_PEDTYPE" depart="233.00">
        <walk edges="gneE0"/>
    </person>
    <person id="176" type="DEFAULT_PEDTYPE" depart="240.00">
        <walk edges="-gneE0 gneE2"/>
    </person>
    <person id="177" type="DEFAULT_PEDTYPE" depart="240.60">
        <walk edges="-gneE0"/>
    </person>
    <person id="180" type="DEFAULT_PEDTYPE" depart="244.80">
        <walk edges="gneE3 gneE1"/>
    </person>
    <person id="182" type="DEFAULT_PEDTYPE" depart="248.80">
        <walk edges="-gneE0"/>
    </person>
    <person id="183" type="DEFAULT_PEDTYPE" depart="249.00">
        <walk edges="gneE0"/>
    </person>
    <person id="185" type="DEFAULT_PEDTYPE" depart="255.20">
        <walk edges="-gneE0 gneE0"/>
    </person>
    <person id="187" type="DEFAULT_PEDTYPE" depart="257.20">
        <walk edges="gneE0"/>
    </person>
    <person id="189" type="DEFAULT_PEDTYPE" depart="263.80">
        <walk edges="gneE0 -gneE0"/>
    </person>
    <person id="190" type="DEFAULT_PEDTYPE" depart="264.60">
        <walk edges="gneE0 -gneE0"/>
    </person>
    <person id="191" type="DEFAULT_PEDTYPE" depart="264.80">
        <walk edges="-gneE0"/>
    </person>
    <person id="193" type="DEFAULT_PEDTYPE" depart="267.60">
        <walk edges="gneE0 -gneE0"/>
    </person>
    <person id="194" type="DEFAULT_PEDTYPE" depart="270.60">
        <walk edges="gneE0 gneE2"/>
    </person>
    <person id="195" type="DEFAULT_PEDTYPE" depart="274.60">
        <walk edges="-gneE0 gneE0"/>
    </person>
    <person id="196" type="DEFAULT_PEDTYPE" depart="277.60">
        <walk edges="-gneE0 gneE0"/>
    </person>
    <person id="198" type="DEFAULT_PEDTYPE" depart="279.80">
        <walk edges="gneE0"/>
    </person>
    <person id="201" type="DEFAULT_PEDTYPE" depart="283.40">
        <walk edges="gneE0"/>
    </person>
    <person id="204" type="DEFAULT_PEDTYPE" depart="286.60">
        <walk edges="-gneE0 gneE0"/>
    </person>
    <person id="206" type="DEFAULT_PEDTYPE" depart="290.40">
        <walk edges="gneE0"/>
    </person>
    <person id="207" type="DEFAULT_PEDTYPE" depart="290.60">
        <walk edges="-gneE0"/>
    </person>
    <person id="208" type="DEFAULT_PEDTYPE" depart="294.40">
        <walk edges="gneE0"/>
    </person>
    <person id="209" type="DEFAULT_PEDTYPE" depart="297.00">
        <walk edges="-gneE0 gneE0"/>
    </person>
    <person id="211" type="DEFAULT_PEDTYPE" depart="304.60">
        <walk edges="gneE1 gneE3"/>
    </person>
    <person id="214" type="DEFAULT_PEDTYPE" depart="307.20">
        <walk edges="gneE0"/>
    </person>
    <person id="216" type="DEFAULT_PEDTYPE" depart="312.40">
        <walk edges="gneE0"/>
    </person>
    <person id="217" type="DEFAULT_PEDTYPE" depart="313.00">
        <walk edges="-gneE0"/>
    </person>
    <person id="221" type="DEFAULT_PEDTYPE" depart="315.20">
        <walk edges="gneE0 -gneE0"/>
    </person>
    <person id="222" type="DEFAULT_PEDTYPE" depart="316.00">
        <walk edges="-gneE0 gneE0"/>
    </person>
    <person id="224" type="DEFAULT_PEDTYPE" depart="318.80">
        <walk edges="-gneE0"/>
    </person>
    <person id="225" type="DEFAULT_PEDTYPE" depart="324.20">
        <walk edges="-gneE0 gneE0"/>
    </person>
    <person id="228" type="DEFAULT_PEDTYPE" depart="326.20">
        <walk edges="gneE0 -gneE0"/>
    </person>
    <person id="230" type="DEFAULT_PEDTYPE" depart="328.00">
        <walk edges="gneE0"/>
    </person>
    <person id="235" type="DEFAULT_PEDTYPE" depart="332.00">
        <walk edges="gneE0"/>
    </person>
    <person id="238" type="DEFAULT_PEDTYPE" depart="335.20">
        <walk edges="gneE0"/>
    </person>
    <person id="239" type="DEFAULT_PEDTYPE" depart="335.40">
        <walk edges="gneE0"/>
    </person>
    <person id="241" type="DEFAULT_PEDTYPE" depart="341.00">
        <walk edges="gneE0"/>
    </person>
    <person id="242" type="DEFAULT_PEDTYPE" depart="341.20">
        <walk edges="gneE1 gneE3"/>
    </person>
    <person id="244" type="DEFAULT_PEDTYPE" depart="341.80">
        <walk edges="-gneE0 gneE2"/>
    </person>
    <person id="245" type="DEFAULT_PEDTYPE" depart="344.80">
        <walk edges="gneE0"/>
    </person>
    <person id="247" type="DEFAULT_PEDTYPE" depart="347.80">
        <walk edges="gneE0 -gneE0"/>
    </person>
    <person id="248" type="DEFAULT_PEDTYPE" depart="348.40">
        <walk edges="-gneE0 gneE2"/>
    </person>
    <person id="250" type="DEFAULT_PEDTYPE" depart="349.80">
        <walk edges="gneE0 -gneE0"/>
    </person>
    <person id="252" type="DEFAULT_PEDTYPE" depart="352.40">
        <walk edges="-gneE0"/>
    </person>
    <person id="253" type="DEFAULT_PEDTYPE" depart="353.00">
        <walk edges="gneE0"/>
    </person>
    <person id="255" type="DEFAULT_PEDTYPE" depart="355.00">
        <walk edges="gneE0 -gneE0"/>
    </person>
    <person id="256" type="DEFAULT_PEDTYPE" depart="355.80">
        <walk edges="-gneE0"/>
    </person>
    <person id="257" type="DEFAULT_PEDTYPE" depart="357.40">
        <walk edges="gneE2 gneE0"/>
    </person>
    <person id="258" type="DEFAULT_PEDTYPE" depart="360.40">
        <walk edges="gneE0"/>
    </person>
    <person id="259" type="DEFAULT_PEDTYPE" depart="360.80">
        <walk edges="-gneE0 gneE0"/>
    </person>
    <person id="260" type="DEFAULT_PEDTYPE" depart="361.60">
        <walk edges="-gneE0 gneE2"/>
    </person>
    <person id="262" type="DEFAULT_PEDTYPE" depart="366.00">
        <walk edges="gneE0 -gneE0"/>
    </person>
    <person id="263" type="DEFAULT_PEDTYPE" depart="366.20">
        <walk edges="gneE0 -gneE0"/>
    </person>
    <person id="266" type="DEFAULT_PEDTYPE" depart="373.80">
        <walk edges="gneE0"/>
    </person>
    <person id="270" type="DEFAULT_PEDTYPE" depart="375.20">
        <walk edges="-gneE0"/>
    </person>
    <person id="272" type="DEFAULT_PEDTYPE" depart="378.80">
        <walk edges="-gneE0 gneE0"/>
    </person>
    <person id="273" type="DEFAULT_PEDTYPE" depart="380.60">
        <walk edges="-gneE0 gneE0"/>
    </person>
    <person id="275" type="DEFAULT_PEDTYPE" depart="382.20">
        <walk edges="-gneE0 gneE0"/>
    </person>
    <person id="276" type="DEFAULT_PEDTYPE" depart="385.20">
        <walk edges="gneE0"/>
    </person>
    <person id="277" type="DEFAULT_PEDTYPE" depart="386.00">
        <walk edges="-gneE0"/>
    </person>
    <person id="278" type="DEFAULT_PEDTYPE" depart="388.60">
        <walk edges="gneE0"/>
    </person>
    <person id="279" type="DEFAULT_PEDTYPE" depart="393.80">
        <walk edges="gneE0 -gneE0"/>
    </person>
    <person id="280" type="DEFAULT_PEDTYPE" depart="394.80">
        <walk edges="-gneE0"/>
    </person>
    <person id="281" type="DEFAULT_PEDTYPE" depart="396.00">
        <walk edges="-gneE0 gneE0"/>
    </person>
    <person id="282" type="DEFAULT_PEDTYPE" depart="399.60">
        <walk edges="gneE3"/>
    </person>
    <person id="283" type="DEFAULT_PEDTYPE" depart="400.40">
        <walk edges="gneE0"/>
    </person>
    <person id="284" type="DEFAULT_PEDTYPE" depart="401.80">
        <walk edges="-gneE0 gneE0"/>
    </person>
    <person id="285" type="DEFAULT_PEDTYPE" depart="407.20">
        <walk edges="gneE0 -gneE0"/>
    </person>
    <person id="286" type="DEFAULT_PEDTYPE" depart="407.60">
        <walk edges="gneE2 gneE0"/>
    </person>
    <person id="288" type="DEFAULT_PEDTYPE" depart="410.00">
        <walk edges="gneE0"/>
    </person>
    <person id="289" type="DEFAULT_PEDTYPE" depart="410.20">
        <walk edges="-gneE0"/>
    </person>
    <person id="290" type="DEFAULT_PEDTYPE" depart="410.40">
        <walk edges="gneE0 -gneE0"/>
    </person>
    <person id="293" type="DEFAULT_PEDTYPE" depart="415.40">
        <walk edges="-gneE0 gneE0"/>
    </person>
    <person id="294" type="DEFAULT_PEDTYPE" depart="416.60">
        <walk edges="-gneE0 gneE0"/>
    </person>
    <person id="295" type="DEFAULT_PEDTYPE" depart="416.60">
        <walk edges="gneE0 -gneE0"/>
    </person>
    <person id="296" type="DEFAULT_PEDTYPE" depart="419.40">
        <walk edges="-gneE0"/>
    </person>
    <person id="297" type="DEFAULT_PEDTYPE" depart="421.00">
        <walk edges="gneE0 -gneE0"/>
    </person>
    <person id="298" type="DEFAULT_PEDTYPE" depart="424.20">
        <walk edges="-gneE0"/>
    </person>
    <person id="301" type="DEFAULT_PEDTYPE" depart="426.20">
        <walk edges="-gneE0 gneE0"/>
    </person>
    <person id="302" type="DEFAULT_PEDTYPE" depart="427.80">
        <walk edges="gneE0"/>
    </person>
    <person id="304" type="DEFAULT_PEDTYPE" depart="433.60">
        <walk edges="gneE0"/>
    </person>
    <person id="305" type="DEFAULT_PEDTYPE" depart="433.80">
        <walk edges="-gneE0 gneE0"/>
    </person>
    <person id="306" type="DEFAULT_PEDTYPE" depart="434.20">
        <walk edges="gneE0"/>
    </person>
    <person id="308" type="DEFAULT_PEDTYPE" depart="436.80">
        <walk edges="gneE0 -gneE0"/>
    </person>
    <person id="310" type="DEFAULT_PEDTYPE" depart="438.00">
        <walk edges="gneE0"/>
    </person>
    <person id="311" type="DEFAULT_PEDTYPE" depart="438.80">
        <walk edges="-gneE0 gneE0"/>
    </person>
    <person id="312" type="DEFAULT_PEDTYPE" depart="438.80">
        <walk edges="gneE2 gneE0"/>
    </person>
    <person id="314" type="DEFAULT_PEDTYPE" depart="442.60">
        <walk edges="gneE0 -gneE0"/>
    </person>
    <person id="315" type="DEFAULT_PEDTYPE" depart="444.00">
        <walk edges="gneE0 -gneE0"/>
    </person>
    <person id="316" type="DEFAULT_PEDTYPE" depart="448.00">
        <walk edges="gneE2 gneE0"/>
    </person>
    <person id="318" type="DEFAULT_PEDTYPE" depart="453.20">
        <walk edges="-gneE0 gneE0"/>
    </person>
    <person id="320" type="DEFAULT_PEDTYPE" depart="459.20">
        <walk edges="gneE0"/>
    </person>
    <person id="321" type="DEFAULT_PEDTYPE" depart="459.80">
        <walk edges="gneE3 gneE1"/>
    </person>
    <person id="327" type="DEFAULT_PEDTYPE" depart="476.20">
        <walk edges="gneE0 -gneE0"/>
    </person>
    <person id="329" type="DEFAULT_PEDTYPE" depart="480.00">
        <walk edges="gneE0 -gneE0"/>
    </person>
    <person id="331" type="DEFAULT_PEDTYPE" depart="480.80">
        <walk edges="gneE0"/>
    </person>
    <person id="334" type="DEFAULT_PEDTYPE" depart="486.60">
        <walk edges="gneE0 -gneE0"/>
    </person>
    <person id="335" type="DEFAULT_PEDTYPE" depart="489.00">
        <walk edges="-gneE0"/>
    </person>
    <person id="336" type="DEFAULT_PEDTYPE" depart="489.80">
        <walk edges="gneE2"/>
    </person>
    <person id="337" type="DEFAULT_PEDTYPE" depart="491.40">
        <walk edges="-gneE0 gneE0"/>
    </person>
    <person id="338" type="DEFAULT_PEDTYPE" depart="492.20">
        <walk edges="gneE0"/>
    </person>
    <person id="340" type="DEFAULT_PEDTYPE" depart="494.40">
        <walk edges="gneE0 -gneE0"/>
    </person>
    <person id="341" type="DEFAULT_PEDTYPE" depart="495.40">
        <walk edges="gneE0 gneE2"/>
    </person>
    <person id="342" type="DEFAULT_PEDTYPE" depart="496.60">
        <walk edges="gneE0 -gneE0"/>
    </person>
    <person id="343" type="DEFAULT_PEDTYPE" depart="496.80">
        <walk edges="-gneE0 gneE0"/>
    </person>
    <person id="344" type="DEFAULT_PEDTYPE" depart="499.60">
        <walk edges="gneE0"/>
    </person>
    <person id="345" type="DEFAULT_PEDTYPE" depart="499.60">
        <walk edges="-gneE0 gneE0"/>
    </person>
    <person id="346" type="DEFAULT_PEDTYPE" depart="502.60">
        <walk edges="-gneE0 gneE0"/>
    </person>
    <person id="347" type="DEFAULT_PEDTYPE" depart="504.60">
        <walk edges="gneE2 -gneE0"/>
    </person>
    <person id="349" type="DEFAULT_PEDTYPE" depart="506.40">
        <walk edges="-gneE0"/>
    </person>
    <person id="351" type="DEFAULT_PEDTYPE" depart="507.80">
        <walk edges="-gneE0 gneE0"/>
    </person>
    <person id="352" type="DEFAULT_PEDTYPE" depart="511.00">
        <walk edges="gneE0"/>
    </person>
    <person id="353" type="DEFAULT_PEDTYPE" depart="511.40">
        <walk edges="-gneE0"/>
    </person>
    <person id="356" type="DEFAULT_PEDTYPE" depart="518.00">
        <walk edges="gneE0"/>
    </person>
    <person id="357" type="DEFAULT_PEDTYPE" depart="519.40">
        <walk edges="gneE0"/>
    </person>
    <person id="358" type="DEFAULT_PEDTYPE" depart="521.00">
        <walk edges="gneE0"/>
    </person>
    <person id="359" type="DEFAULT_PEDTYPE" depart="521.40">
        <walk edges="gneE2 -gneE0"/>
    </person>
    <person id="360" type="DEFAULT_PEDTYPE" depart="521.60">
        <walk edges="gneE0"/>
    </person>
    <person id="365" type="DEFAULT_PEDTYPE" depart="529.20">
        <walk edges="gneE0 -gneE0"/>
    </person>
    <person id="370" type="DEFAULT_PEDTYPE" depart="536.20">
        <walk edges="-gneE0 gneE0"/>
    </person>
    <person id="372" type="DEFAULT_PEDTYPE" depart="538.60">
        <walk edges="gneE2 -gneE0"/>
    </person>
    <person id="373" type="DEFAULT_PEDTYPE" depart="539.00">
        <walk edges="-gneE0 gneE2"/>
    </person>
    <person id="374" type="DEFAULT_PEDTYPE" depart="541.40">
        <walk edges="-gneE0"/>
    </person>
    <person id="380" type="DEFAULT_PEDTYPE" depart="548.80">
        <walk edges="gneE0"/>
    </person>
    <person id="383" type="DEFAULT_PEDTYPE" depart="553.80">
        <walk edges="-gneE0 gneE0"/>
    </person>
    <person id="384" type="DEFAULT_PEDTYPE" depart="555.20">
        <walk edges="-gneE0 gneE0"/>
    </person>
    <person id="385" type="DEFAULT_PEDTYPE" depart="555.40">
        <walk edges="gneE0 -gneE0"/>
    </person>
    <person id="387" type="DEFAULT_PEDTYPE" depart="559.20">
        <walk edges="gneE0"/>
    </person>
    <person id="388" type="DEFAULT_PEDTYPE" depart="559.40">
        <walk edges="gneE1 gneE3"/>
    </person>
    <person id="389" type="DEFAULT_PEDTYPE" depart="559.80">
        <walk edges="gneE2"/>
    </person>
    <person id="390" type="DEFAULT_PEDTYPE" depart="563.00">
        <walk edges="gneE0 -gneE0"/>
    </person>
    <person id="391" type="DEFAULT_PEDTYPE" depart="565.60">
        <walk edges="-gneE0"/>
    </person>
    <person id="393" type="DEFAULT_PEDTYPE" depart="568.60">
        <walk edges="-gneE0"/>
    </person>
    <person id="394" type="DEFAULT_PEDTYPE" depart="573.00">
        <walk edges="gneE1"/>
    </person>
    <person id="395" type="DEFAULT_PEDTYPE" depart="573.60">
        <walk edges="gneE0"/>
    </person>
    <person id="396" type="DEFAULT_PEDTYPE" depart="574.40">
        <walk edges="gneE0"/>
    </person>
    <person id="397" type="DEFAULT_PEDTYPE" depart="575.00">
        <walk edges="-gneE0 gneE2"/>
    </person>
    <person id="398" type="DEFAULT_PEDTYPE" depart="575.80">
        <walk edges="-gneE0 gneE2"/>
    </person>
    <person id="400" type="DEFAULT_PEDTYPE" depart="580.00">
        <walk edges="-gneE0 gneE2"/>
    </person>
    <person id="402" type="DEFAULT_PEDTYPE" depart="584.80">
        <walk edges="-gneE0 gneE2"/>
    </person>
    <person id="403" type="DEFAULT_PEDTYPE" depart="587.40">
        <walk edges="gneE1 gneE3"/>
    </person>
    <person id="404" type="DEFAULT_PEDTYPE" depart="593.00">
        <walk edges="gneE2 gneE0"/>
    </person>
    <person id="405" type="DEFAULT_PEDTYPE" depart="593.60">
        <walk edges="-gneE0"/>
    </person>
    <person id="406" type="DEFAULT_PEDTYPE" depart="594.00">
        <walk edges="-gneE0 gneE0"/>
    </person>
    <person id="407" type="DEFAULT_PEDTYPE" depart="596.00">
        <walk edges="gneE1 gneE3"/>
    </person>
    <person id="408" type="DEFAULT_PEDTYPE" depart="596.40">
        <walk edges="-gneE0"/>
    </person>
    <person id="409" type="DEFAULT_PEDTYPE" depart="597.40">
        <walk edges="-gneE0 gneE0"/>
    </person>
    <person id="410" type="DEFAULT_PEDTYPE" depart="599.00">
        <walk edges="gneE0 -gneE0"/>
    </person>
    <person id="411" type="DEFAULT_PEDTYPE" depart="601.80">
        <walk edges="-gneE0 gneE0"/>
    </person>
    <person id="412" type="DEFAULT_PEDTYPE" depart="603.40">
        <walk edges="-gneE0"/>
    </person>
    <person id="413" type="DEFAULT_PEDTYPE" depart="604.00">
        <walk edges="gneE2 -gneE0"/>
    </person>
    <person id="414" type="DEFAULT_PEDTYPE" depart="605.00">
        <walk edges="gneE0"/>
    </person>
    <person id="415" type="DEFAULT_PEDTYPE" depart="607.00">
        <walk edges="gneE0 gneE2"/>
    </person>
    <person id="416" type="DEFAULT_PEDTYPE" depart="614.00">
        <walk edges="-gneE0 gneE0"/>
    </person>
    <person id="417" type="DEFAULT_PEDTYPE" depart="615.20">
        <walk edges="-gneE0"/>
    </person>
    <person id="418" type="DEFAULT_PEDTYPE" depart="616.60">
        <walk edges="-gneE0 gneE0"/>
    </person>
    <person id="420" type="DEFAULT_PEDTYPE" depart="622.00">
        <walk edges="gneE0 -gneE0"/>
    </person>
    <person id="421" type="DEFAULT_PEDTYPE" depart="623.80">
        <walk edges="gneE2 -gneE0"/>
    </person>
    <person id="422" type="DEFAULT_PEDTYPE" depart="623.80">
        <walk edges="gneE2 -gneE0"/>
    </person>
    <person id="423" type="DEFAULT_PEDTYPE" depart="624.00">
        <walk edges="-gneE0"/>
    </person>
    <person id="424" type="DEFAULT_PEDTYPE" depart="624.20">
        <walk edges="-gneE0"/>
    </person>
    <person id="425" type="DEFAULT_PEDTYPE" depart="626.00">
        <walk edges="gneE0 -gneE0"/>
    </person>
    <person id="426" type="DEFAULT_PEDTYPE" depart="626.20">
        <walk edges="gneE0"/>
    </person>
    <person id="427" type="DEFAULT_PEDTYPE" depart="629.20">
        <walk edges="gneE0"/>
    </person>
    <person id="428" type="DEFAULT_PEDTYPE" depart="629.80">
        <walk edges="-gneE0"/>
    </person>
    <person id="429" type="DEFAULT_PEDTYPE" depart="631.20">
        <walk edges="-gneE0 gneE2"/>
    </person>
    <person id="430" type="DEFAULT_PEDTYPE" depart="631.60">
        <walk edges="-gneE0 gneE0"/>
    </person>
    <person id="432" type="DEFAULT_PEDTYPE" depart="635.00">
        <walk edges="-gneE0 gneE0"/>
    </person>
    <person id="434" type="DEFAULT_PEDTYPE" depart="637.20">
        <walk edges="gneE1 gneE3"/>
    </person>
    <person id="435" type="DEFAULT_PEDTYPE" depart="637.80">
        <walk edges="gneE0"/>
    </person>
    <person id="436" type="DEFAULT_PEDTYPE" depart="638.00">
        <walk edges="gneE0 -gneE0"/>
    </person>
    <person id="437" type="DEFAULT_PEDTYPE" depart="639.00">
        <walk edges="gneE0 -gneE0"/>
    </person>
    <person id="439" type="DEFAULT_PEDTYPE" depart="641.20">
        <walk edges="gneE0 -gneE0"/>
    </person>
    <person id="441" type="DEFAULT_PEDTYPE" depart="643.80">
        <walk edges="gneE0 -gneE0"/>
    </person>
    <person id="442" type="DEFAULT_PEDTYPE" depart="644.20">
        <walk edges="gneE0"/>
    </person>
    <person id="443" type="DEFAULT_PEDTYPE" depart="647.20">
        <walk edges="gneE1"/>
    </person>
    <person id="444" type="DEFAULT_PEDTYPE" depart="648.60">
        <walk edges="gneE0 -gneE0"/>
    </person>
    <person id="445" type="DEFAULT_PEDTYPE" depart="649.40">
        <walk edges="-gneE0"/>
    </person>
    <person id="446" type="DEFAULT_PEDTYPE" depart="651.00">
        <walk edges="gneE0"/>
    </person>
    <person id="447" type="DEFAULT_PEDTYPE" depart="652.60">
        <walk edges="-gneE0 gneE0"/>
    </person>
    <person id="448" type="DEFAULT_PEDTYPE" depart="655.60">
        <walk edges="-gneE0 gneE0"/>
    </person>
    <person id="449" type="DEFAULT_PEDTYPE" depart="660.60">
        <walk edges="gneE0"/>
    </person>
    <person id="451" type="DEFAULT_PEDTYPE" depart="666.60">
        <walk edges="gneE0 -gneE0"/>
    </person>
    <person id="453" type="DEFAULT_PEDTYPE" depart="671.00">
        <walk edges="gneE0 -gneE0"/>
    </person>
    <person id="455" type="DEFAULT_PEDTYPE" depart="672.40">
        <walk edges="-gneE0 gneE0"/>
    </person>
    <person id="456" type="DEFAULT_PEDTYPE" depart="675.00">
        <walk edges="-gneE0"/>
    </person>
    <person id="457" type="DEFAULT_PEDTYPE" depart="675.40">
        <walk edges="gneE0"/>
    </person>
    <person id="458" type="DEFAULT_PEDTYPE" depart="676.00">
        <walk edges="gneE0 -gneE0"/>
    </person>
    <person id="459" type="DEFAULT_PEDTYPE" depart="677.20">
        <walk edges="-gneE0 gneE0"/>
    </person>
    <person id="460" type="DEFAULT_PEDTYPE" depart="679.00">
        <walk edges="gneE1"/>
    </person>
    <person id="461" type="DEFAULT_PEDTYPE" depart="679.40">
        <walk edges="gneE1 gneE3"/>
    </person>
    <person id="463" type="DEFAULT_PEDTYPE" depart="680.80">
        <walk edges="-gneE0"/>
    </person>
    <person id="464" type="DEFAULT_PEDTYPE" depart="682.60">
        <walk edges="-gneE0"/>
    </person>
    <person id="468" type="DEFAULT_PEDTYPE" depart="688.20">
        <walk edges="gneE0 -gneE0"/>
    </person>
    <person id="469" type="DEFAULT_PEDTYPE" depart="688.40">
        <walk edges="-gneE0 gneE0"/>
    </person>
    <person id="470" type="DEFAULT_PEDTYPE" depart="689.40">
        <walk edges="-gneE0"/>
    </person>
    <person id="471" type="DEFAULT_PEDTYPE" depart="689.60">
        <walk edges="-gneE0"/>
    </person>
    <person id="473" type="DEFAULT_PEDTYPE" depart="697.60">
        <walk edges="gneE0 -gneE0"/>
    </person>
    <person id="475" type="DEFAULT_PEDTYPE" depart="699.60">
        <walk edges="gneE2 -gneE0"/>
    </person>
    <person id="476" type="DEFAULT_PEDTYPE" depart="699.80">
        <walk edges="-gneE0"/>
    </person>
    <person id="478" type="DEFAULT_PEDTYPE" depart="701.20">
        <walk edges="gneE2 gneE0"/>
    </person>
    <person id="479" type="DEFAULT_PEDTYPE" depart="702.00">
        <walk edges="gneE1 gneE3"/>
    </person>
    <person id="482" type="DEFAULT_PEDTYPE" depart="706.40">
        <walk edges="gneE0"/>
    </person>
    <person id="484" type="DEFAULT_PEDTYPE" depart="708.20">
        <walk edges="-gneE0"/>
    </person>
    <person id="487" type="DEFAULT_PEDTYPE" depart="710.80">
        <walk edges="-gneE0 gneE0"/>
    </person>
    <person id="488" type="DEFAULT_PEDTYPE" depart="714.20">
        <walk edges="-gneE0 gneE0"/>
    </person>
    <person id="489" type="DEFAULT_PEDTYPE" depart="714.60">
        <walk edges="gneE2"/>
    </person>
    <person id="490" type="DEFAULT_PEDTYPE" depart="715.20">
        <walk edges="-gneE0 gneE0"/>
    </person>
    <person id="492" type="DEFAULT_PEDTYPE" depart="719.80">
        <walk edges="gneE0 -gneE0"/>
    </person>
    <person id="493" type="DEFAULT_PEDTYPE" depart="720.20">
        <walk edges="gneE3"/>
    </person>
    <person id="495" type="DEFAULT_PEDTYPE" depart="721.60">
        <walk edges="gneE2 gneE0"/>
    </person>
    <person id="496" type="DEFAULT_PEDTYPE" depart="722.20">
        <walk edges="gneE0"/>
    </person>
    <person id="497" type="DEFAULT_PEDTYPE" depart="722.60">
        <walk edges="gneE0 -gneE0"/>
    </person>
    <person id="498" type="DEFAULT_PEDTYPE" depart="723.00">
        <walk edges="gneE0 -gneE0"/>
    </person>
    <person id="500" type="DEFAULT_PEDTYPE" depart="724.60">
        <walk edges="gneE0"/>
    </person>
    <person id="502" type="DEFAULT_PEDTYPE" depart="725.20">
        <walk edges="gneE0"/>
    </person>
    <person id="503" type="DEFAULT_PEDTYPE" depart="725.80">
        <walk edges="gneE0 -gneE0"/>
    </person>
    <person id="504" type="DEFAULT_PEDTYPE" depart="726.80">
        <walk edges="gneE1 gneE3"/>
    </person>
    <person id="505" type="DEFAULT_PEDTYPE" depart="730.40">
        <walk edges="-gneE0"/>
    </person>
    <person id="507" type="DEFAULT_PEDTYPE" depart="731.20">
        <walk edges="-gneE0"/>
    </person>
    <person id="509" type="DEFAULT_PEDTYPE" depart="734.20">
        <walk edges="gneE0"/>
    </person>
    <person id="510" type="DEFAULT_PEDTYPE" depart="736.80">
        <walk edges="-gneE0 gneE0"/>
    </person>
    <person id="512" type="DEFAULT_PEDTYPE" depart="737.40">
        <walk edges="gneE0 -gneE0"/>
    </person>
    <person id="514" type="DEFAULT_PEDTYPE" depart="740.60">
        <walk edges="-gneE0 gneE0"/>
    </person>
    <person id="515" type="DEFAULT_PEDTYPE" depart="741.00">
        <walk edges="gneE0 -gneE0"/>
    </person>
    <person id="516" type="DEFAULT_PEDTYPE" depart="743.00">
        <walk edges="gneE2 gneE0"/>
    </person>
    <person id="518" type="DEFAULT_PEDTYPE" depart="749.60">
        <walk edges="gneE0 -gneE0"/>
    </person>
    <person id="519" type="DEFAULT_PEDTYPE" depart="750.20">
        <walk edges="-gneE0 gneE0"/>
    </person>
    <person id="520" type="DEFAULT_PEDTYPE" depart="757.40">
        <walk edges="-gneE0"/>
    </person>
    <person id="523" type="DEFAULT_PEDTYPE" depart="761.40">
        <walk edges="gneE0 -gneE0"/>
    </person>
    <person id="524" type="DEFAULT_PEDTYPE" depart="761.40">
        <walk edges="gneE3"/>
    </person>
    <person id="525" type="DEFAULT_PEDTYPE" depart="761.60">
        <walk edges="gneE0 -gneE0"/>
    </person>
    <person id="526" type="DEFAULT_PEDTYPE" depart="762.20">
        <walk edges="gneE2 gneE0"/>
    </person>
    <person id="527" type="DEFAULT_PEDTYPE" depart="762.60">
        <walk edges="-gneE0"/>
    </person>
    <person id="529" type="DEFAULT_PEDTYPE" depart="769.00">
        <walk edges="-gneE0 gneE2"/>
    </person>
    <person id="530" type="DEFAULT_PEDTYPE" depart="769.80">
        <walk edges="gneE0 -gneE0"/>
    </person>
    <person id="531" type="DEFAULT_PEDTYPE" depart="770.60">
        <walk edges="-gneE0 gneE2"/>
    </person>
    <person id="533" type="DEFAULT_PEDTYPE" depart="771.80">
        <walk edges="gneE2 -gneE0"/>
    </person>
    <person id="539" type="DEFAULT_PEDTYPE" depart="777.20">
        <walk edges="-gneE0"/>
    </person>
    <person id="541" type="DEFAULT_PEDTYPE" depart="778.80">
        <walk edges="gneE0 gneE2"/>
    </person>
    <person id="542" type="DEFAULT_PEDTYPE" depart="779.00">
        <walk edges="-gneE0"/>
    </person>
    <person id="543" type="DEFAULT_PEDTYPE" depart="779.00">
        <walk edges="gneE0"/>
    </person>
    <person id="544" type="DEFAULT_PEDTYPE" depart="780.40">
        <walk edges="gneE0"/>
    </person>
    <person id="546" type="DEFAULT_PEDTYPE" depart="787.00">
        <walk edges="gneE3"/>
    </person>
    <person id="548" type="DEFAULT_PEDTYPE" depart="788.00">
        <walk edges="gneE0 gneE2"/>
    </person>
    <person id="550" type="DEFAULT_PEDTYPE" depart="789.00">
        <walk edges="gneE0"/>
    </person>
    <person id="551" type="DEFAULT_PEDTYPE" depart="793.20">
        <walk edges="gneE0 -gneE0"/>
    </person>
    <person id="552" type="DEFAULT_PEDTYPE" depart="794.00">
        <walk edges="gneE3 gneE1"/>
    </person>
    <person id="553" type="DEFAULT_PEDTYPE" depart="798.80">
        <walk edges="gneE0 -gneE0"/>
    </person>
    <person id="554" type="DEFAULT_PEDTYPE" depart="799.20">
        <walk edges="gneE0 -gneE0"/>
    </person>
    <person id="556" type="DEFAULT_PEDTYPE" depart="807.80">
        <walk edges="-gneE0"/>
    </person>
    <person id="557" type="DEFAULT_PEDTYPE" depart="808.00">
        <walk edges="-gneE0"/>
    </person>
    <person id="558" type="DEFAULT_PEDTYPE" depart="808.60">
        <walk edges="-gneE0 gneE0"/>
    </person>
    <person id="561" type="DEFAULT_PEDTYPE" depart="813.00">
        <walk edges="-gneE0 gneE0"/>
    </person>
    <person id="562" type="DEFAULT_PEDTYPE" depart="813.60">
        <walk edges="-gneE0 gneE0"/>
    </person>
    <person id="563" type="DEFAULT_PEDTYPE" depart="813.80">
        <walk edges="-gneE0"/>
    </person>
    <person id="564" type="DEFAULT_PEDTYPE" depart="813.80">
        <walk edges="-gneE0 gneE0"/>
    </person>
    <person id="566" type="DEFAULT_PEDTYPE" depart="816.80">
        <walk edges="gneE0 -gneE0"/>
    </person>
    <person id="568" type="DEFAULT_PEDTYPE" depart="819.20">
        <walk edges="gneE0"/>
    </person>
    <person id="569" type="DEFAULT_PEDTYPE" depart="820.60">
        <walk edges="-gneE0 gneE0"/>
    </person>
    <person id="570" type="DEFAULT_PEDTYPE" depart="821.60">
        <walk edges="gneE0 -gneE0"/>
    </person>
    <person id="571" type="DEFAULT_PEDTYPE" depart="821.60">
        <walk edges="-gneE0"/>
    </person>
    <person id="572" type="DEFAULT_PEDTYPE" depart="822.20">
        <walk edges="-gneE0"/>
    </person>
    <person id="573" type="DEFAULT_PEDTYPE" depart="824.80">
        <walk edges="gneE0 gneE2"/>
    </person>
    <person id="574" type="DEFAULT_PEDTYPE" depart="826.60">
        <walk edges="-gneE0"/>
    </person>
    <person id="580" type="DEFAULT_PEDTYPE" depart="832.00">
        <walk edges="gneE0 gneE2"/>
    </person>
    <person id="581" type="DEFAULT_PEDTYPE" depart="834.40">
        <walk edges="-gneE0 gneE0"/>
    </person>
    <person id="582" type="DEFAULT_PEDTYPE" depart="834.60">
        <walk edges="gneE0 -gneE0"/>
    </person>
    <person id="583" type="DEFAULT_PEDTYPE" depart="835.20">
        <walk edges="gneE3"/>
    </person>
    <person id="585" type="DEFAULT_PEDTYPE" depart="840.80">
        <walk edges="-gneE0 gneE0"/>
    </person>
    <person id="589" type="DEFAULT_PEDTYPE" depart="845.00">
        <walk edges="gneE0"/>
    </person>
    <person id="590" type="DEFAULT_PEDTYPE" depart="846.00">
        <walk edges="-gneE0 gneE0"/>
    </person>
    <person id="591" type="DEFAULT_PEDTYPE" depart="847.00">
        <walk edges="gneE0 -gneE0"/>
    </person>
    <person id="592" type="DEFAULT_PEDTYPE" depart="847.00">
        <walk edges="gneE2 gneE0"/>
    </person>
    <person id="594" type="DEFAULT_PEDTYPE" depart="849.80">
        <walk edges="-gneE0"/>
    </person>
    <person id="596" type="DEFAULT_PEDTYPE" depart="855.40">
        <walk edges="gneE2 gneE0"/>
    </person>
    <person id="599" type="DEFAULT_PEDTYPE" depart="860.80">
        <walk edges="gneE0 -gneE0"/>
    </person>
    <person id="600" type="DEFAULT_PEDTYPE" depart="861.80">
        <walk edges="gneE0"/>
    </person>
    <person id="601" type="DEFAULT_PEDTYPE" depart="862.20">
        <walk edges="-gneE0 gneE0"/>
    </person>
    <person id="602" type="DEFAULT_PEDTYPE" depart="863.40">
        <walk edges="gneE0 -gneE0"/>
    </person>
    <person id="604" type="DEFAULT_PEDTYPE" depart="863.80">
        <walk edges="gneE0 -gneE0"/>
    </person>
    <person id="605" type="DEFAULT_PEDTYPE" depart="864.40">
        <walk edges="gneE0"/>
    </person>
    <person id="606" type="DEFAULT_PEDTYPE" depart="865.40">
        <walk edges="gneE0 gneE2"/>
    </person>
    <person id="608" type="DEFAULT_PEDTYPE" depart="868.00">
        <walk edges="gneE0 -gneE0"/>
    </person>
    <person id="610" type="DEFAULT_PEDTYPE" depart="870.20">
        <walk edges="-gneE0"/>
    </person>
    <person id="612" type="DEFAULT_PEDTYPE" depart="875.20">
        <walk edges="gneE0 -gneE0"/>
    </person>
    <person id="615" type="DEFAULT_PEDTYPE" depart="880.40">
        <walk edges="gneE0 gneE2"/>
    </person>
    <person id="616" type="DEFAULT_PEDTYPE" depart="881.80">
        <walk edges="gneE0"/>
    </person>
    <person id="617" type="DEFAULT_PEDTYPE" depart="882.40">
        <walk edges="gneE0 -gneE0"/>
    </person>
    <person id="618" type="DEFAULT_PEDTYPE" depart="883.60">
        <walk edges="gneE0"/>
    </person>
    <person id="619" type="DEFAULT_PEDTYPE" depart="886.80">
        <walk edges="-gneE0"/>
    </person>
    <person id="620" type="DEFAULT_PEDTYPE" depart="887.40">
        <walk edges="gneE0 -gneE0"/>
    </person>
    <person id="621" type="DEFAULT_PEDTYPE" depart="888.00">
        <walk edges="gneE2 gneE0"/>
    </person>
    <person id="624" type="DEFAULT_PEDTYPE" depart="892.60">
        <walk edges="gneE0 gneE2"/>
    </person>
    <person id="625" type="DEFAULT_PEDTYPE" depart="894.60">
        <walk edges="gneE0 -gneE0"/>
    </person>
    <person id="626" type="DEFAULT_PEDTYPE" depart="895.40">
        <walk edges="gneE0 -gneE0"/>
    </person>
    <person id="627" type="DEFAULT_PEDTYPE" depart="895.40">
        <walk edges="gneE2"/>
    </person>
    <person id="628" type="DEFAULT_PEDTYPE" depart="896.80">
        <walk edges="gneE3"/>
    </person>
    <person id="630" type="DEFAULT_PEDTYPE" depart="899.20">
        <walk edges="-gneE0 gneE0"/>
    </person>
    <person id="631" type="DEFAULT_PEDTYPE" depart="899.80">
        <walk edges="-gneE0 gneE0"/>
    </person>
    <person id="633" type="DEFAULT_PEDTYPE" depart="903.80">
        <walk edges="-gneE0 gneE0"/>
    </person>
    <person id="634" type="DEFAULT_PEDTYPE" depart="904.00">
        <walk edges="gneE2 -gneE0"/>
    </person>
    <person id="635" type="DEFAULT_PEDTYPE" depart="907.00">
        <walk edges="gneE0"/>
    </person>
    <person id="637" type="DEFAULT_PEDTYPE" depart="909.00">
        <walk edges="gneE0 -gneE0"/>
    </person>
    <person id="638" type="DEFAULT_PEDTYPE" depart="911.80">
        <walk edges="gneE0 -gneE0"/>
    </person>
    <person id="639" type="DEFAULT_PEDTYPE" depart="911.80">
        <walk edges="gneE0"/>
    </person>
    <person id="640" type="DEFAULT_PEDTYPE" depart="912.00">
        <walk edges="-gneE0"/>
    </person>
    <person id="641" type="DEFAULT_PEDTYPE" depart="912.80">
        <walk edges="-gneE0"/>
    </person>
    <person id="642" type="DEFAULT_PEDTYPE" depart="913.20">
        <walk edges="gneE0 -gneE0"/>
    </person>
    <person id="644" type="DEFAULT_PEDTYPE" depart="914.60">
        <walk edges="-gneE0 gneE0"/>
    </person>
    <person id="647" type="DEFAULT_PEDTYPE" depart="917.20">
        <walk edges="gneE1 gneE3"/>
    </person>
    <person id="648" type="DEFAULT_PEDTYPE" depart="917.60">
        <walk edges="-gneE0"/>
    </person>
    <person id="649" type="DEFAULT_PEDTYPE" depart="917.80">
        <walk edges="-gneE0 gneE0"/>
    </person>
    <person id="650" type="DEFAULT_PEDTYPE" depart="918.60">
        <walk edges="-gneE0"/>
    </person>
    <person id="652" type="DEFAULT_PEDTYPE" depart="928.00">
        <walk edges="gneE0 -gneE0"/>
    </person>
    <person id="653" type="DEFAULT_PEDTYPE" depart="929.20">
        <walk edges="-gneE0 gneE0"/>
    </person>
    <person id="656" type="DEFAULT_PEDTYPE" depart="934.80">
        <walk edges="-gneE0 gneE0"/>
    </person>
    <person id="657" type="DEFAULT_PEDTYPE" depart="935.20">
        <walk edges="-gneE0"/>
    </person>
    <person id="658" type="DEFAULT_PEDTYPE" depart="936.60">
        <walk edges="gneE0 gneE2"/>
    </person>
    <person id="660" type="DEFAULT_PEDTYPE" depart="938.80">
        <walk edges="gneE0"/>
    </person>
    <person id="661" type="DEFAULT_PEDTYPE" depart="941.20">
        <walk edges="gneE0 gneE2"/>
    </person>
    <person id="664" type="DEFAULT_PEDTYPE" depart="943.00">
        <walk edges="gneE0 -gneE0"/>
    </person>
    <person id="665" type="DEFAULT_PEDTYPE" depart="948.00">
        <walk edges="-gneE0"/>
    </person>
    <person id="666" type="DEFAULT_PEDTYPE" depart="950.40">
        <walk edges="-gneE0"/>
    </person>
    <person id="667" type="DEFAULT_PEDTYPE" depart="950.40">
        <walk edges="gneE0 -gneE0"/>
    </person>
    <person id="669" type="DEFAULT_PEDTYPE" depart="951.00">
        <walk edges="-gneE0"/>
    </person>
    <person id="670" type="DEFAULT_PEDTYPE" depart="951.40">
        <walk edges="-gneE0 gneE0"/>
    </person>
    <person id="671" type="DEFAULT_PEDTYPE" depart="952.20">
        <walk edges="gneE0 -gneE0"/>
    </person>
    <person id="672" type="DEFAULT_PEDTYPE" depart="952.60">
        <walk edges="gneE0"/>
    </person>
    <person id="673" type="DEFAULT_PEDTYPE" depart="953.00">
        <walk edges="-gneE0"/>
    </person>
    <person id="674" type="DEFAULT_PEDTYPE" depart="953.20">
        <walk edges="gneE0 -gneE0"/>
    </person>
    <person id="675" type="DEFAULT_PEDTYPE" depart="953.40">
        <walk edges="gneE0 -gneE0"/>
    </person>
    <person id="676" type="DEFAULT_PEDTYPE" depart="954.00">
        <walk edges="-gneE0"/>
    </person>
    <person id="677" type="DEFAULT_PEDTYPE" depart="955.20">
        <walk edges="-gneE0 gneE0"/>
    </person>
    <person id="678" type="DEFAULT_PEDTYPE" depart="955.60">
        <walk edges="gneE0 -gneE0"/>
    </person>
    <person id="679" type="DEFAULT_PEDTYPE" depart="956.40">
        <walk edges="-gneE0 gneE0"/>
    </person>
    <person id="680" type="DEFAULT_PEDTYPE" depart="959.40">
        <walk edges="gneE2 gneE0"/>
    </person>
    <person id="683" type="DEFAULT_PEDTYPE" depart="966.20">
        <walk edges="gneE0 -gneE0"/>
    </person>
    <person id="685" type="DEFAULT_PEDTYPE" depart="968.80">
        <walk edges="-gneE0 gneE0"/>
    </person>
    <person id="686" type="DEFAULT_PEDTYPE" depart="969.00">
        <walk edges="gneE0"/>
    </person>
    <person id="687" type="DEFAULT_PEDTYPE" depart="969.20">
        <walk edges="gneE2 -gneE0"/>
    </person>
    <person id="688" type="DEFAULT_PEDTYPE" depart="970.00">
        <walk edges="-gneE0"/>
    </person>
    <person id="689" type="DEFAULT_PEDTYPE" depart="971.00">
        <walk edges="gneE3 gneE1"/>
    </person>
    <person id="690" type="DEFAULT_PEDTYPE" depart="971.20">
        <walk edges="gneE0 -gneE0"/>
    </person>
    <person id="691" type="DEFAULT_PEDTYPE" depart="971.20">
        <walk edges="gneE0"/>
    </person>
    <person id="692" type="DEFAULT_PEDTYPE" depart="971.60">
        <walk edges="gneE0"/>
    </person>
    <person id="693" type="DEFAULT_PEDTYPE" depart="972.60">
        <walk edges="gneE2 gneE0"/>
    </person>
    <person id="694" type="DEFAULT_PEDTYPE" depart="973.40">
        <walk edges="-gneE0"/>
    </person>
    <person id="696" type="DEFAULT_PEDTYPE" depart="975.60">
        <walk edges="gneE2 gneE0"/>
    </person>
    <person id="699" type="DEFAULT_PEDTYPE" depart="978.20">
        <walk edges="-gneE0 gneE2"/>
    </person>
    <person id="700" type="DEFAULT_PEDTYPE" depart="978.80">
        <walk edges="-gneE0 gneE2"/>
    </person>
    <person id="702" type="DEFAULT_PEDTYPE" depart="978.80">
        <walk edges="gneE2 gneE0"/>
    </person>
    <person id="703" type="DEFAULT_PEDTYPE" depart="981.00">
        <walk edges="gneE0 gneE2"/>
    </person>
    <person id="704" type="DEFAULT_PEDTYPE" depart="981.00">
        <walk edges="gneE0 -gneE0"/>
    </person>
    <person id="705" type="DEFAULT_PEDTYPE" depart="981.40">
        <walk edges="gneE0 -gneE0"/>
    </person>
    <person id="707" type="DEFAULT_PEDTYPE" depart="985.60">
        <walk edges="gneE0 gneE2"/>
    </person>
    <person id="709" type="DEFAULT_PEDTYPE" depart="985.80">
        <walk edges="-gneE0 gneE0"/>
    </person>
    <person id="710" type="DEFAULT_PEDTYPE" depart="989.40">
        <walk edges="gneE0"/>
    </person>
    <person id="712" type="DEFAULT_PEDTYPE" depart="993.20">
        <walk edges="gneE0"/>
    </person>
    <person id="713" type="DEFAULT_PEDTYPE" depart="995.20">
        <walk edges="gneE0 -gneE0"/>
    </person>
</routes>
